exchange_interface/__init__.py
exchange_interface/creds.py
exchange_interface-0.0.4.dist-info/METADATA
exchange_interface-0.0.4.dist-info/WHEEL
exchange_interface-0.0.4.dist-info/top_level.txt
exchange_interface-0.0.4.dist-info/RECORD
