Metadata-Version: 2.1
Name: exchange-interface
Version: 0.0.4
Summary: An interface to Microsoft Exchange Web Services (EWS). Allows the user to manipulate the outlook calendar events.
Home-page: https://github.com/GrantGMiller/exchange_interface
Author: Grant miller
Author-email: grant@grant-miller.com
License: PSF
Project-URL: Source Code, https://github.com/GrantGMiller/exchange_interface
Keywords: grant miller microsoft office365 ews
Platform: UNKNOWN
Requires-Dist: calendar-base
Requires-Dist: requests
